django_urls/__init__.py
django_urls-1.1.4.dist-info/LICENSE
django_urls-1.1.4.dist-info/METADATA
django_urls-1.1.4.dist-info/WHEEL
django_urls-1.1.4.dist-info/top_level.txt
django_urls-1.1.4.dist-info/RECORD
