Metadata-Version: 2.1
Name: django_urls
Version: 1.1.4
Summary: URL decorator for django views
Home-page: https://github.com/isik-kaplan/django_urls
Author: isik-kaplan
Author-email: 
License: MIT LICENSE
Classifier: License :: OSI Approved :: MIT License
Classifier: Programming Language :: Python :: 3
Classifier: Framework :: Django
Classifier: Development Status :: 5 - Production/Stable
Requires-Python: >=3.5
License-File: LICENSE
Requires-Dist: django>=2.0
